{"data":{"provinceId":"13","countyName":"涿鹿县","townList":[{"id":"11000336","name":"县城"},{"id":"1069656","name":"保岱镇"},{"id":"1069684","name":"城关镇"},{"id":"1069712","name":"大堡镇"},{"id":"1069779","name":"矾山镇"},{"id":"300286758","name":"河东镇"},{"id":"1069906","name":"五堡镇"},{"id":"3110885","name":"武家沟镇"},{"id":"1069977","name":"张家堡镇"},{"id":"300061898","name":"涿鹿镇"},{"id":"300286757","name":"大河南乡"},{"id":"1069760","name":"东小庄乡"},{"id":"1069805","name":"黑山寺乡"},{"id":"1069815","name":"辉耀乡"},{"id":"1069850","name":"栾庄乡"},{"id":"1069867","name":"蟒石口乡"},{"id":"1069902","name":"卧佛寺乡"},{"id":"1069891","name":"温泉屯乡"},{"id":"300286759","name":"谢家堡乡"},{"id":"1069992","name":"赵家蓬乡"}],"cityId":"1307","cityName":"张家口市","provinceName":"河北省","countyId":"130731"},"success":"true"}
