{"data":{"provinceId":"14","countyName":"浑源县","townList":[{"id":"11000399","name":"县城"},{"id":"1097471","name":"蔡村镇"},{"id":"1097482","name":"大磁窑镇"},{"id":"1097712","name":"沙圪坨镇"},{"id":"3000718","name":"王堡镇"},{"id":"1097766","name":"王庄堡镇"},{"id":"1097822","name":"西坊城镇"},{"id":"1097864","name":"永安镇"},{"id":"1097517","name":"东坊城乡"},{"id":"1097495","name":"大仁庄乡"},{"id":"1097536","name":"官儿乡"},{"id":"1097575","name":"黄花滩乡"},{"id":"1097609","name":"南榆林乡"},{"id":"1097630","name":"裴村乡"},{"id":"1097683","name":"青磁窑乡"},{"id":"1097645","name":"千佛岭乡"},{"id":"1097748","name":"驼峰乡"},{"id":"1097800","name":"吴城乡"},{"id":"300307113","name":"下韩村乡"},{"id":"310078163","name":"西韩岭乡"},{"id":"1097846","name":"下韩乡"},{"id":"1097834","name":"西留村乡"},{"id":"1097835","name":"西留乡"},{"id":"3000719","name":"赵北乡"}],"cityId":"1402","cityName":"大同市","provinceName":"山西省","countyId":"140225"},"success":"true"}
