{"data":{"provinceId":"14","countyName":"广灵县","townList":[{"id":"11000397","name":"县城"},{"id":"1096967","name":"壶泉镇"},{"id":"1097054","name":"南村镇"},{"id":"1096957","name":"斗泉乡"},{"id":"1096998","name":"加斗乡"},{"id":"1097015","name":"蕉山乡"},{"id":"1097035","name":"梁庄乡"},{"id":"1097097","name":"望狐乡"},{"id":"3000448","name":"一斗泉乡"},{"id":"1097139","name":"宜兴乡"},{"id":"3000449","name":"作町乡"},{"id":"1097160","name":"作疃乡"}],"cityId":"1402","cityName":"大同市","provinceName":"山西省","countyId":"140223"},"success":"true"}
