{"data":{"provinceId":"14","countyName":"忻府区","townList":[{"id":"11000083","name":"城区"},{"id":"1118937","name":"播明镇"},{"id":"3000473","name":"董村镇"},{"id":"1119021","name":"豆罗镇"},{"id":"1119376","name":"奇村镇"},{"id":"1119445","name":"三交镇"},{"id":"11216851","name":"轩岗镇"},{"id":"1119670","name":"庄磨镇"},{"id":"3000468","name":"北义井乡"},{"id":"3000470","name":"曹张乡"},{"id":"3000467","name":"东楼乡"},{"id":"3000477","name":"高城乡"},{"id":"3000469","name":"合索乡"},{"id":"3000475","name":"解原乡"},{"id":"1119247","name":"兰村乡"},{"id":"1119345","name":"牛尾乡"},{"id":"300327567","name":"坡陡乡"},{"id":"3000471","name":"秦城乡"},{"id":"3000466","name":"上社乡"},{"id":"3000465","name":"上寺乡"},{"id":"3000474","name":"西张乡"},{"id":"3000476","name":"阳坡乡"},{"id":"3000472","name":"紫岩乡"},{"id":"1119574","name":"忻定农牧场"}],"cityId":"1409","cityName":"忻州市","provinceName":"山西省","countyId":"140902"},"success":"true"}
