{"data":{"provinceId":"15","countyName":"乌兰浩特市","townList":[{"id":"11000425","name":"县城"},{"id":"11253490","name":"阿尔本格勒镇"},{"id":"11253513","name":"阿拉达尔吐镇"},{"id":"11253495","name":"巴达尔胡镇"},{"id":"11253494","name":"巴岱镇"},{"id":"11253492","name":"宝力根花镇"},{"id":"11253467","name":"宝石镇"},{"id":"11253497","name":"巴彦高勒镇"},{"id":"11253481","name":"杜尔基镇"},{"id":"11056180","name":"葛根庙镇"},{"id":"300286267","name":"归流河镇"},{"id":"11253491","name":"胡尔乐镇"},{"id":"3109392","name":"居力很镇"},{"id":"11253488","name":"六户镇"},{"id":"11253485","name":"水泉镇"},{"id":"300286266","name":"太本镇"},{"id":"300286268","name":"卫东镇"},{"id":"3107137","name":"乌兰哈达镇"},{"id":"11253499","name":"乌塔其图牧吉镇"},{"id":"11253508","name":"新林镇"},{"id":"11253465","name":"永安镇"},{"id":"11253496","name":"音德尔镇"},{"id":"3107127","name":"义勒力特镇"},{"id":"3111026","name":"永联镇"},{"id":"11253503","name":"巴彦扎拉嘎乡"},{"id":"11253489","name":"城郊乡"},{"id":"11253512","name":"都尔本新乡"},{"id":"11253493","name":"二龙山乡"},{"id":"11253498","name":"好力保乡"},{"id":"11253470","name":"哈拉沁乡"},{"id":"11253477","name":"巨力乡"},{"id":"11253473","name":"九龙乡"},{"id":"11253511","name":"努恩木仁乡"},{"id":"11253468","name":"太东乡"},{"id":"11253472","name":"太和乡"},{"id":"11253462","name":"太平乡"},{"id":"11253506","name":"五家户乡"},{"id":"11253510","name":"小城子乡"},{"id":"11253464","name":"溪柳乡"},{"id":"11253474","name":"学田乡"}],"cityId":"1522","cityName":"兴安盟","provinceName":"内蒙古自治区","countyId":"152201"},"success":"true"}
