{"data":{"provinceId":"21","countyName":"溪湖区","townList":[{"id":"11000484","name":"城区"},{"id":"300285579","name":"边牛镇"},{"id":"300215526","name":"北台镇"},{"id":"11255025","name":"东凤镇"},{"id":"3106997","name":"东风镇"},{"id":"1165203","name":"高台子镇"},{"id":"1165224","name":"火连寨镇"},{"id":"300215513","name":"牛心台镇"},{"id":"11066575","name":"桥头镇"},{"id":"3112196","name":"石桥子镇"},{"id":"300215523","name":"卧龙镇"},{"id":"3110899","name":"歪头山镇"},{"id":"11057894","name":"东风乡"},{"id":"3102725","name":"张其寨乡"}],"cityId":"2105","cityName":"本溪市","provinceName":"辽宁省","countyId":"210503"},"success":"true"}
