{"data":{"provinceId":"23","countyName":"阿城区","townList":[{"id":"11000613","name":"城区"},{"id":"1199620","name":"蜚克图镇"},{"id":"1199635","name":"交界镇"},{"id":"300310432","name":"金龙山镇"},{"id":"1199677","name":"巨源镇"},{"id":"1199704","name":"平山镇"},{"id":"1199721","name":"松峰山镇"},{"id":"1199716","name":"双丰镇"},{"id":"11189123","name":"王岗镇"},{"id":"3110031","name":"新华镇"},{"id":"1199762","name":"小岭镇"},{"id":"1199771","name":"亚沟镇"},{"id":"1199815","name":"玉泉镇"},{"id":"1199812","name":"永源镇"},{"id":"3105934","name":"阿什河乡"},{"id":"1199615","name":"大岭乡"},{"id":"1199628","name":"红星乡"},{"id":"11186308","name":"料甸满族乡"},{"id":"1199681","name":"利新乡"},{"id":"1199710","name":"舍利乡"},{"id":"1199767","name":"新乡乡"},{"id":"1199809","name":"杨树乡"},{"id":"12002041","name":"农场"},{"id":"310123237","name":"山河林场"}],"cityId":"2301","cityName":"哈尔滨市","provinceName":"黑龙江省","countyId":"230112"},"success":"true"}
