{"data":{"provinceId":"23","countyName":"甘南县","townList":[{"id":"11000634","name":"县城"},{"id":"1204128","name":"东阳镇"},{"id":"1204148","name":"甘南镇"},{"id":"1204173","name":"巨宝镇"},{"id":"1204188","name":"平阳镇"},{"id":"1204208","name":"音河镇"},{"id":"1204075","name":"宝山乡"},{"id":"1204092","name":"查哈阳乡"},{"id":"300310516","name":"兴隆乡"},{"id":"1204099","name":"长吉岗乡"},{"id":"1204111","name":"长山乡"},{"id":"1204216","name":"中兴乡"},{"id":"1204087","name":"查哈阳农场"},{"id":"1204172","name":"金边农场"},{"id":"1204195","name":"双河农场"}],"cityId":"2302","cityName":"齐齐哈尔市","provinceName":"黑龙江省","countyId":"230225"},"success":"true"}
