{"data":{"provinceId":"23","countyName":"肇东市","townList":[{"id":"11000730","name":"县城"},{"id":"1218967","name":"昌五镇"},{"id":"1219040","name":"姜家镇"},{"id":"1219081","name":"里木店镇"},{"id":"1219077","name":"黎明镇"},{"id":"1219052","name":"涝洲镇"},{"id":"1219118","name":"尚家镇"},{"id":"300465707","name":"胜利镇"},{"id":"1219143","name":"宋站镇"},{"id":"1219136","name":"四站镇"},{"id":"11191335","name":"王岗镇"},{"id":"1219166","name":"五里明镇"},{"id":"1219175","name":"五站镇"},{"id":"1219232","name":"肇东镇"},{"id":"1218950","name":"安民乡"},{"id":"1218981","name":"德昌乡"},{"id":"1218991","name":"东发乡"},{"id":"1219016","name":"海城乡"},{"id":"1219024","name":"洪河乡"},{"id":"1219099","name":"明久乡"},{"id":"1219153","name":"太平乡"},{"id":"1219182","name":"西八里乡"},{"id":"3102315","name":"宣化乡"},{"id":"1219193","name":"先进乡"},{"id":"1219194","name":"向阳乡"},{"id":"1219222","name":"跃进乡"},{"id":"310098412","name":"涝洲鱼种场"},{"id":"300061448","name":"民益路"},{"id":"300060776","name":"南七街"},{"id":"300060770","name":"人民大街"},{"id":"310032932","name":"四方山农场"},{"id":"300060777","name":"行署街"},{"id":"300060774","name":"正街"},{"id":"300060775","name":"肇兰路"}],"cityId":"2312","cityName":"绥化市","provinceName":"黑龙江省","countyId":"231282"},"success":"true"}
