{"data":{"provinceId":"32","countyName":"六合区","townList":[{"id":"11000768","name":"城区"},{"id":"310122035","name":"八佰桥镇"},{"id":"3107496","name":"八百桥镇"},{"id":"11070335","name":"八百镇"},{"id":"3112389","name":"程桥镇"},{"id":"11276136","name":"大厂镇"},{"id":"3106950","name":"东沟镇"},{"id":"11276152","name":"顶山镇"},{"id":"300490024","name":"大圣镇"},{"id":"11276342","name":"东旺镇"},{"id":"11073133","name":"冯集镇"},{"id":"310192182","name":"樊集镇"},{"id":"1238768","name":"瓜埠镇"},{"id":"11276156","name":"葛塘镇"},{"id":"3110838","name":"横梁镇"},{"id":"11276337","name":"花旗镇"},{"id":"11276343","name":"合镇"},{"id":"300459091","name":"江浦镇"},{"id":"300218426","name":"龙池街镇"},{"id":"310122036","name":"六城镇"},{"id":"300465431","name":"禄口镇"},{"id":"3114533","name":"龙袍镇"},{"id":"11073132","name":"灵岩镇"},{"id":"3114104","name":"马鞍镇"},{"id":"3114101","name":"马集镇"},{"id":"300335653","name":"穆林镇"},{"id":"11276133","name":"桥林镇"},{"id":"300490023","name":"泉水镇"},{"id":"300277841","name":"四合镇"},{"id":"11276145","name":"石桥镇"},{"id":"300311805","name":"汤泉镇"},{"id":"11276183","name":"泰山镇"},{"id":"300465430","name":"陶吴镇"},{"id":"300311807","name":"乌江镇"},{"id":"11276155","name":"星甸镇"},{"id":"11276201","name":"新簧镇"},{"id":"3110173","name":"新篁镇"},{"id":"3110193","name":"新集镇"},{"id":"11072177","name":"雄州镇"},{"id":"1238981","name":"雄洲镇"},{"id":"3111821","name":"玉带镇"},{"id":"11276141","name":"永丰镇"},{"id":"300311808","name":"永宁镇"},{"id":"3107624","name":"冶山镇"},{"id":"11276203","name":"竹程镇"},{"id":"11276138","name":"珠江镇"},{"id":"300490025","name":"钟林镇"},{"id":"11074841","name":"长芦镇"},{"id":"310207705","name":"长山镇"},{"id":"310193307","name":"钱仓乡"},{"id":"300490026","name":"乌石乡"},{"id":"300104650","name":"长江农场"}],"cityId":"3201","cityName":"南京市","provinceName":"江苏省","countyId":"320116"},"success":"true"}
