{"data":{"provinceId":"32","countyName":"沛县","townList":[{"id":"11000503","name":"县城"},{"id":"1252841","name":"安国镇"},{"id":"1254161","name":"崔寨镇"},{"id":"300351206","name":"大黄山镇"},{"id":"300337970","name":"大庙镇"},{"id":"1253032","name":"大屯镇"},{"id":"300278788","name":"大许镇"},{"id":"1253206","name":"河口镇"},{"id":"3111618","name":"湖屯镇"},{"id":"1253516","name":"胡寨镇"},{"id":"1254199","name":"郝寨镇"},{"id":"1253707","name":"敬安镇"},{"id":"300278772","name":"贾汪镇"},{"id":"1254041","name":"龙固镇"},{"id":"300351335","name":"利国镇"},{"id":"1254425","name":"鹿楼镇"},{"id":"300351201","name":"柳泉镇"},{"id":"300351337","name":"柳新镇"},{"id":"300374755","name":"庙山镇"},{"id":"1254506","name":"沛城镇"},{"id":"1254735","name":"栖山镇"},{"id":"1254773","name":"唐楼镇"},{"id":"300276331","name":"塘镇"},{"id":"1237926","name":"五段镇"},{"id":"1254791","name":"王店镇"},{"id":"1254803","name":"魏庙镇"},{"id":"300272238","name":"吴镇"},{"id":"11072141","name":"新大屯镇"},{"id":"300351361","name":"徐庄镇"},{"id":"1254494","name":"闫集镇"},{"id":"1254870","name":"鸳楼镇"},{"id":"1254848","name":"杨屯镇"},{"id":"300351233","name":"郑集镇"},{"id":"300351202","name":"张集镇"},{"id":"1254945","name":"朱王庄镇"},{"id":"1254883","name":"张寨镇"},{"id":"300278740","name":"紫庄镇"},{"id":"3110397","name":"朱寨镇"},{"id":"1254913","name":"张庄镇"},{"id":"1254323","name":"湖西农场"}],"cityId":"3203","cityName":"徐州市","provinceName":"江苏省","countyId":"320322"},"success":"true"}
