{"data":{"provinceId":"32","countyName":"东海县","townList":[{"id":"11000819","name":"县城"},{"id":"1280715","name":"安峰镇"},{"id":"11283344","name":"板浦镇"},{"id":"11283343","name":"板桥镇"},{"id":"1280745","name":"白塔埠镇"},{"id":"1280765","name":"房山镇"},{"id":"1280847","name":"黄川镇"},{"id":"11283321","name":"横沟镇"},{"id":"1280828","name":"洪庄镇"},{"id":"11283340","name":"锦屏镇"},{"id":"11283338","name":"连岛镇"},{"id":"11283325","name":"南辰镇"},{"id":"1280893","name":"牛山镇"},{"id":"1281027","name":"平明镇"},{"id":"1281052","name":"浦南镇"},{"id":"1281083","name":"青湖镇"},{"id":"300490792","name":"石埠镇"},{"id":"1281196","name":"双店镇"},{"id":"1281156","name":"石梁河镇"},{"id":"1281172","name":"石榴镇"},{"id":"1281214","name":"桃林镇"},{"id":"1281263","name":"温泉镇"},{"id":"11283346","name":"新坝镇"},{"id":"11283345","name":"高公岛乡"},{"id":"1280813","name":"横沟乡"},{"id":"1280870","name":"李埝乡"},{"id":"1280883","name":"南辰乡"},{"id":"1281105","name":"曲阳乡"},{"id":"1281137","name":"石埠乡"},{"id":"11283341","name":"宿城乡"},{"id":"1281142","name":"石湖乡"},{"id":"1281119","name":"山左口乡"},{"id":"1281237","name":"驼峰乡"},{"id":"1281274","name":"张湾乡"},{"id":"1280763","name":"东海农场"},{"id":"1280795","name":"岗埠农场"},{"id":"300123155","name":"劳改农场"}],"cityId":"3207","cityName":"连云港市","provinceName":"江苏省","countyId":"320722"},"success":"true"}
