{"data":{"provinceId":"33","countyName":"永康市","townList":[{"id":"11000924","name":"县城"},{"id":"11292031","name":"八字墙镇"},{"id":"3110206","name":"方岩镇"},{"id":"11292016","name":"古丽镇"},{"id":"1411193","name":"古山镇"},{"id":"1411348","name":"花街镇"},{"id":"11292030","name":"胡库镇"},{"id":"3114465","name":"龙山镇"},{"id":"11292044","name":"琅琊镇"},{"id":"11292018","name":"廿三里镇"},{"id":"3107712","name":"前仓镇"},{"id":"3107804","name":"千祥镇"},{"id":"11292037","name":"桥下镇"},{"id":"11292033","name":"清溪镇"},{"id":"11292015","name":"四路镇"},{"id":"3112194","name":"石柱镇"},{"id":"3108279","name":"唐先镇"},{"id":"11292043","name":"塘雅镇"},{"id":"1412360","name":"西溪镇"},{"id":"3113209","name":"象珠镇"},{"id":"3112700","name":"舟山镇"},{"id":"11292014","name":"芝英镇"},{"id":"300494595","name":"柏岩乡"},{"id":"11292040","name":"沙畈乡"},{"id":"300494597","name":"棠西乡"},{"id":"310206974","name":"新店乡"},{"id":"11292036","name":"新楼乡"},{"id":"11292041","name":"源东乡"},{"id":"11292039","name":"永祥乡"},{"id":"310206997","name":"中山乡"},{"id":"11292042","name":"长山乡"}],"cityId":"3307","cityName":"金华市","provinceName":"浙江省","countyId":"330784"},"success":"true"}
