{"data":{"provinceId":"35","countyName":"安溪县","townList":[{"id":"11001098","name":"县城"},{"id":"300496758","name":"安溪官桥镇"},{"id":"3108560","name":"城厢镇"},{"id":"3107655","name":"凤城镇"},{"id":"300224385","name":"逢莱镇"},{"id":"3109882","name":"感德镇"},{"id":"3109211","name":"官桥镇"},{"id":"3113012","name":"虎邱镇"},{"id":"3111615","name":"湖头镇"},{"id":"3107725","name":"剑斗镇"},{"id":"3113574","name":"金谷镇"},{"id":"3114221","name":"魁斗镇"},{"id":"3114539","name":"龙门镇"},{"id":"3112739","name":"芦田镇"},{"id":"3112977","name":"蓬莱镇"},{"id":"3113079","name":"西坪镇"},{"id":"3104553","name":"白濑乡"},{"id":"3101328","name":"参内乡"},{"id":"3101896","name":"大坪乡"},{"id":"300337798","name":"福田乡"},{"id":"3104151","name":"湖上乡"},{"id":"3106583","name":"龙涓乡"},{"id":"300286273","name":"蓝田乡"},{"id":"3102418","name":"尚卿乡"},{"id":"3103526","name":"桃舟乡"},{"id":"3104799","name":"祥华乡"},{"id":"1517370","name":"长坑乡"},{"id":"12002339","name":"半林林场"},{"id":"1517463","name":"城乡镇经兜洋乌内农场"}],"cityId":"3505","cityName":"泉州市","provinceName":"福建省","countyId":"350524"},"success":"true"}
