{"data":{"provinceId":"37","countyName":"东港区","townList":[{"id":"11001330","name":"城区"},{"id":"300432012","name":"碑郭镇"},{"id":"1660459","name":"陈疃镇"},{"id":"11087298","name":"大坡镇"},{"id":"300356859","name":"汾水镇"},{"id":"310134028","name":"孤山镇"},{"id":"11087121","name":"高兴镇"},{"id":"11083917","name":"后村镇"},{"id":"11087295","name":"黄墩镇"},{"id":"300432013","name":"虎山镇"},{"id":"1660507","name":"河山镇"},{"id":"310134053","name":"黄土坎镇"},{"id":"300432014","name":"巨峰镇"},{"id":"1660624","name":"两城镇"},{"id":"11314504","name":"李宁镇"},{"id":"1660692","name":"南湖镇"},{"id":"310134039","name":"菩萨庙镇"},{"id":"1660837","name":"三庄镇"},{"id":"1660954","name":"涛雒镇"},{"id":"1661042","name":"西湖镇"},{"id":"11314455","name":"中楼镇"},{"id":"3104902","name":"管帅乡"},{"id":"300356858","name":"前三岛乡"},{"id":"1660927","name":"竖旗乡"},{"id":"3102427","name":"尹家河乡"}],"cityId":"3711","cityName":"日照市","provinceName":"山东省","countyId":"371102"},"success":"true"}
