{"data":{"provinceId":"41","countyName":"偃师市","townList":[{"id":"11001418","name":"县城"},{"id":"11319827","name":"安乐镇"},{"id":"3108456","name":"城关镇"},{"id":"3107375","name":"佃庄镇"},{"id":"3109694","name":"府店镇"},{"id":"1728134","name":"高龙镇"},{"id":"11319826","name":"关林镇"},{"id":"1728154","name":"缑氏镇"},{"id":"3113984","name":"顾县镇"},{"id":"3109264","name":"寇店镇"},{"id":"1728241","name":"李村镇"},{"id":"3105656","name":"邙岭镇"},{"id":"300506711","name":"邙山镇"},{"id":"1728314","name":"庞村镇"},{"id":"3114008","name":"首阳山镇"},{"id":"1728417","name":"岳滩镇"},{"id":"1728476","name":"诸葛镇"},{"id":"11089200","name":"翟镇镇"},{"id":"3101874","name":"大口乡"},{"id":"3100718","name":"佛光乡"},{"id":"300506706","name":"红山乡"},{"id":"3102444","name":"山化乡"}],"cityId":"4103","cityName":"洛阳市","provinceName":"河南省","countyId":"410381"},"success":"true"}
