{"data":{"provinceId":"41","countyName":"汝州市","townList":[{"id":"11001428","name":"县城"},{"id":"11320131","name":"北渡镇"},{"id":"330007995","name":"大峪镇"},{"id":"1731566","name":"寄料镇"},{"id":"1731617","name":"临汝镇"},{"id":"330007998","name":"米庙镇"},{"id":"310016768","name":"汝州镇"},{"id":"1731856","name":"温泉镇"},{"id":"1731939","name":"小屯镇"},{"id":"11090966","name":"焦村乡"},{"id":"1731650","name":"陵头乡"},{"id":"1731682","name":"蟒川乡"},{"id":"1731724","name":"庙下乡"},{"id":"11090963","name":"骑岭乡"},{"id":"1731777","name":"尚庄乡"},{"id":"1731817","name":"王寨乡"},{"id":"3101839","name":"夏店乡"},{"id":"1732010","name":"杨楼乡"},{"id":"1732069","name":"纸坊乡"}],"cityId":"4104","cityName":"平顶山市","provinceName":"河南省","countyId":"410482"},"success":"true"}
