{"data":{"provinceId":"41","countyName":"固始县","townList":[{"id":"11001516","name":"县城"},{"id":"300317177","name":"包信镇"},{"id":"3108470","name":"城关镇"},{"id":"11092354","name":"陈淋子镇"},{"id":"300317169","name":"东岳镇"},{"id":"11092357","name":"方集镇"},{"id":"11092360","name":"郭陆滩镇"},{"id":"1775779","name":"胡族铺镇"},{"id":"11092351","name":"蒋集镇"},{"id":"1775809","name":"黎集镇"},{"id":"11092355","name":"往流镇"},{"id":"11092359","name":"汪棚镇"},{"id":"300317179","name":"项店镇"},{"id":"300317176","name":"小茴店镇"},{"id":"300317172","name":"夏庄镇"},{"id":"300317171","name":"八里岔乡"},{"id":"300317175","name":"白土店乡"},{"id":"300317178","name":"曹黄林乡"},{"id":"1775590","name":"陈集乡"},{"id":"3101760","name":"城郊乡"},{"id":"11092356","name":"草庙集乡"},{"id":"300317168","name":"陈棚乡"},{"id":"1775653","name":"段集乡"},{"id":"11092353","name":"丰港乡"},{"id":"11092482","name":"分水亭乡"},{"id":"300317174","name":"关店乡"},{"id":"300317173","name":"岗李店乡"},{"id":"3105479","name":"观堂乡"},{"id":"1775724","name":"洪埠乡"},{"id":"1775833","name":"李店乡"},{"id":"300317181","name":"临河乡"},{"id":"300317180","name":"路口乡"},{"id":"1775869","name":"柳树店乡"},{"id":"11323395","name":"马岗集乡"},{"id":"1775920","name":"南大桥乡"},{"id":"300317166","name":"彭店乡"},{"id":"1775951","name":"桥沟乡"},{"id":"1775970","name":"泉河铺乡"},{"id":"11095554","name":"泉河乡"},{"id":"11092361","name":"石佛店乡"},{"id":"1775988","name":"三河尖乡"},{"id":"11092352","name":"沙河铺乡"},{"id":"300317167","name":"孙庙乡"},{"id":"1776099","name":"武庙集乡"},{"id":"11095551","name":"武庙乡"},{"id":"3102788","name":"徐集乡"},{"id":"300317182","name":"杨店乡"},{"id":"1776161","name":"杨集乡"},{"id":"11092358","name":"张广庙乡"},{"id":"1776223","name":"赵岗乡"},{"id":"1776201","name":"张老埠乡"},{"id":"300317170","name":"长陵乡"},{"id":"11095560","name":"祖师乡"},{"id":"300317165","name":"张陶乡"},{"id":"12002011","name":"农场"}],"cityId":"4115","cityName":"信阳市","provinceName":"河南省","countyId":"411525"},"success":"true"}
