{"data":{"provinceId":"41","countyName":"扶沟县","townList":[{"id":"11001521","name":"县城"},{"id":"11095939","name":"汴岗镇"},{"id":"1777670","name":"白潭镇"},{"id":"3107743","name":"包屯镇"},{"id":"11094376","name":"城关镇"},{"id":"1777846","name":"崔桥镇"},{"id":"1777907","name":"大新镇"},{"id":"1777982","name":"江村镇"},{"id":"1778024","name":"韭园镇"},{"id":"1778067","name":"练寺镇"},{"id":"3112615","name":"老冢镇"},{"id":"3101182","name":"北郊乡"},{"id":"1777784","name":"柴岗乡"},{"id":"3101764","name":"城郊乡"},{"id":"1777761","name":"曹里乡"},{"id":"1777883","name":"大李庄乡"},{"id":"1777942","name":"固城乡"},{"id":"300288702","name":"何庄乡"},{"id":"1778098","name":"吕潭乡"},{"id":"3104111","name":"清河驿乡"},{"id":"3104118","name":"清集乡"},{"id":"300288703","name":"田庙乡"},{"id":"1778121","name":"农牧场"}],"cityId":"4116","cityName":"周口市","provinceName":"河南省","countyId":"411621"},"success":"true"}
