{"data":{"provinceId":"42","countyName":"汉口镇","townList":[{"id":"11000005","name":"县城"},{"id":"300363471","name":"柏泉镇"},{"id":"300511529","name":"邓南镇"},{"id":"300363472","name":"东山镇"},{"id":"300433006","name":"摩卡小镇"},{"id":"300388536","name":"沙口镇"},{"id":"300363474","name":"新沟镇"},{"id":"300363473","name":"辛家渡镇"},{"id":"300363497","name":"燕岭镇"},{"id":"300380221","name":"走马岭集镇"},{"id":"300455179","name":"长丰乡"}],"cityId":"4201","cityName":"武汉市","provinceName":"湖北省","countyId":"420119"},"success":"true"}
