{"data":{"provinceId":"42","countyName":"樊城区","townList":[{"id":"11001582","name":"城区"},{"id":"11192395","name":"城关镇"},{"id":"11192428","name":"程河镇"},{"id":"300513050","name":"东津镇"},{"id":"300473753","name":"法龙镇"},{"id":"300473757","name":"谷驿镇"},{"id":"300473758","name":"黄集镇"},{"id":"11193425","name":"黑龙集镇"},{"id":"300473755","name":"黄龙镇"},{"id":"11328770","name":"伙牌镇"},{"id":"11328776","name":"林捕镇"},{"id":"300473759","name":"龙王镇"},{"id":"1809333","name":"米庄镇"},{"id":"11328769","name":"泥沮镇"},{"id":"11328777","name":"泥咀镇"},{"id":"1809344","name":"牛首镇"},{"id":"11194797","name":"欧庙镇"},{"id":"11195373","name":"双沟镇"},{"id":"11195357","name":"柿铺镇"},{"id":"300473760","name":"石桥镇"},{"id":"1809413","name":"太平店镇"},{"id":"1809473","name":"团山镇"},{"id":"11328780","name":"卧龙镇"},{"id":"300235279","name":"肖湾镇"},{"id":"300473752","name":"尹集镇"},{"id":"300473754","name":"峪山镇"},{"id":"11196880","name":"张家集镇"},{"id":"300473756","name":"朱集镇"},{"id":"11197083","name":"竹条镇"},{"id":"11328767","name":"张湾镇"},{"id":"11192016","name":"白湾乡"},{"id":"300097432","name":"庞公乡"},{"id":"11195355","name":"柿铺乡"},{"id":"11195717","name":"王寨乡"},{"id":"300294662","name":"余岗乡"},{"id":"300512973","name":"杨家河乡"},{"id":"11328778","name":"尹集乡"},{"id":"11197070","name":"朱坡乡"},{"id":"1809263","name":"高新区"},{"id":"300180429","name":"胡杨家"}],"cityId":"4206","cityName":"襄阳市","provinceName":"湖北省","countyId":"420606"},"success":"true"}
