{"data":{"provinceId":"43","countyName":"辰溪县","townList":[{"id":"11001743","name":"县城"},{"id":"1901375","name":"安坪镇"},{"id":"1901421","name":"辰阳镇"},{"id":"1901525","name":"火马冲镇"},{"id":"1901508","name":"黄溪口镇"},{"id":"1901694","name":"寺前镇"},{"id":"1901735","name":"潭湾镇"},{"id":"1901755","name":"田湾镇"},{"id":"11097345","name":"王安坪镇"},{"id":"1901821","name":"孝坪镇"},{"id":"1901391","name":"板桥乡"},{"id":"1901437","name":"城郊乡"},{"id":"1901454","name":"船溪乡"},{"id":"1901468","name":"大水田乡"},{"id":"300319126","name":"后塘瑶族乡"},{"id":"1901551","name":"锦滨乡"},{"id":"1901559","name":"龙泉岩乡"},{"id":"1901571","name":"龙头庵乡"},{"id":"300319124","name":"罗子山瑶族乡"},{"id":"1901601","name":"桥头溪乡"},{"id":"1901643","name":"石碧乡"},{"id":"1901693","name":"水井乡"},{"id":"1901659","name":"石马湾乡"},{"id":"300319128","name":"苏木溪瑶族乡"},{"id":"300319127","name":"上蒲溪瑶族乡"},{"id":"1901674","name":"柿溪乡"},{"id":"1901719","name":"谭家场乡"},{"id":"1901770","name":"伍家湾乡"},{"id":"1901803","name":"小龙门乡"},{"id":"300319125","name":"仙人湾瑶族乡"},{"id":"1901843","name":"修溪乡"},{"id":"1901859","name":"中伙铺乡"},{"id":"1901403","name":"长田湾乡"}],"cityId":"4312","cityName":"怀化市","provinceName":"湖南省","countyId":"431223"},"success":"true"}
