{"data":{"provinceId":"44","countyName":"德庆县","townList":[{"id":"11001840","name":"县城"},{"id":"2181031","name":"播植镇"},{"id":"300164487","name":"德城镇"},{"id":"2181153","name":"德城镇"},{"id":"11376049","name":"德回龙镇"},{"id":"300297192","name":"德庆镇"},{"id":"2181289","name":"凤村镇"},{"id":"2181457","name":"高良镇"},{"id":"2181674","name":"官圩镇"},{"id":"11376044","name":"怀城镇"},{"id":"2181898","name":"回龙镇"},{"id":"2182026","name":"九市镇"},{"id":"2182260","name":"莫村镇"},{"id":"2182149","name":"马圩镇"},{"id":"11114592","name":"南江口镇"},{"id":"11376043","name":"南街镇"},{"id":"11114595","name":"沙傍镇"},{"id":"300244575","name":"沙浦镇"},{"id":"2182446","name":"武垄镇"},{"id":"2182521","name":"新圩镇"},{"id":"2182520","name":"新圩镇"},{"id":"11124333","name":"新墟镇"},{"id":"2182751","name":"悦城镇"},{"id":"2182645","name":"永丰镇"}],"cityId":"4412","cityName":"肇庆市","provinceName":"广东省","countyId":"441226"},"success":"true"}
