{"data":{"provinceId":"44","countyName":"湘桥区","townList":[{"id":"11001880","name":"城区"},{"id":"11118965","name":"庵埠镇"},{"id":"11386654","name":"宝山镇"},{"id":"11386573","name":"赤凤镇"},{"id":"11118962","name":"彩塘镇"},{"id":"11386647","name":"大埕镇"},{"id":"11118968","name":"东凤镇"},{"id":"11386641","name":"东山镇"},{"id":"11386658","name":"大山镇"},{"id":"11386572","name":"登塘镇"},{"id":"300245622","name":"大镇"},{"id":"11386637","name":"浮滨镇"},{"id":"11386576","name":"凤凰镇"},{"id":"11386643","name":"浮山镇"},{"id":"11118966","name":"凤塘镇"},{"id":"11118969","name":"枫溪镇"},{"id":"11118971","name":"浮洋镇"},{"id":"11386575","name":"归湖镇"},{"id":"11386636","name":"高堂镇"},{"id":"11118959","name":"官塘镇"},{"id":"11118957","name":"古巷镇"},{"id":"11386640","name":"海山镇"},{"id":"300456938","name":"河溪镇"},{"id":"11118958","name":"江东镇"},{"id":"11386639","name":"建饶镇"},{"id":"11118960","name":"金石镇"},{"id":"11118961","name":"龙湖镇"},{"id":"11386638","name":"联饶镇"},{"id":"11118964","name":"磷溪镇"},{"id":"11386648","name":"坪溪镇"},{"id":"310091720","name":"桥东镇"},{"id":"11386635","name":"汫洲镇"},{"id":"11386644","name":"饶洋镇"},{"id":"11386651","name":"所城镇"},{"id":"11386652","name":"三饶镇"},{"id":"11386642","name":"上饶镇"},{"id":"11118963","name":"沙溪镇"},{"id":"11118970","name":"铁铺镇"},{"id":"11386578","name":"文祠镇"},{"id":"11118967","name":"乌洋镇"},{"id":"11386653","name":"新丰镇"},{"id":"11386650","name":"新塘镇"},{"id":"11386646","name":"新圩镇"},{"id":"11386628","name":"奄埠镇"},{"id":"2290194","name":"意溪镇"},{"id":"11386645","name":"柘林镇"},{"id":"11386649","name":"樟溪镇"},{"id":"3100325","name":"东郊新乡"},{"id":"310239642","name":"东埔乡"},{"id":"3101954","name":"大新乡"},{"id":"11386632","name":"凤南乡"},{"id":"3101025","name":"凤新街道莲云管理区前乡"},{"id":"2288673","name":"后街顶乡"},{"id":"2288713","name":"后街下乡"},{"id":"11386567","name":"河内十八乡"},{"id":"2288616","name":"河内四宁东乡"},{"id":"2288842","name":"吉利乡"},{"id":"2289379","name":"沙洲上洲乡"},{"id":"3100185","name":"上洲乡"},{"id":"2289416","name":"沙洲下洲乡"},{"id":"11386633","name":"田东乡"},{"id":"3100223","name":"下津乡"},{"id":"11386662","name":"溪口乡"},{"id":"300169929","name":"新桥路"}],"cityId":"4451","cityName":"潮州市","provinceName":"广东省","countyId":"445102"},"success":"true"}
