{"data":{"provinceId":"45","countyName":"钦北区","townList":[{"id":"11001952","name":"城区"},{"id":"300292785","name":"安石镇"},{"id":"3110548","name":"板城镇"},{"id":"300292803","name":"白石水镇"},{"id":"300292793","name":"北通镇"},{"id":"300292789","name":"大成镇"},{"id":"3108754","name":"大寺镇"},{"id":"3108741","name":"大垌镇"},{"id":"3108862","name":"大直镇"},{"id":"300292802","name":"福旺镇"},{"id":"3113219","name":"贵台镇"},{"id":"11392344","name":"黄屋屯镇"},{"id":"300292786","name":"江城镇"},{"id":"11392299","name":"久隆镇"},{"id":"300292791","name":"江宁镇"},{"id":"11392396","name":"康熙岭镇"},{"id":"300292800","name":"龙门镇"},{"id":"300292787","name":"乐民镇"},{"id":"300292801","name":"六垠镇"},{"id":"11392387","name":"茅岭镇"},{"id":"11392347","name":"那丽镇"},{"id":"3113407","name":"那蒙镇"},{"id":"11392390","name":"那彭镇"},{"id":"11176275","name":"那垌镇"},{"id":"3113410","name":"那香镇"},{"id":"3109595","name":"平吉镇"},{"id":"300292792","name":"平睦镇"},{"id":"300292795","name":"泉水镇"},{"id":"3113916","name":"青塘镇"},{"id":"300292804","name":"三合镇"},{"id":"300292790","name":"石桶镇"},{"id":"3109360","name":"小董镇"},{"id":"3110127","name":"新棠镇"},{"id":"300292788","name":"张黄镇"},{"id":"300292799","name":"樟家镇"},{"id":"3113725","name":"长滩镇"},{"id":"300292797","name":"寨圩镇"}],"cityId":"4507","cityName":"钦州市","provinceName":"广西壮族自治区","countyId":"450703"},"success":"true"}
