{"data":{"provinceId":"46","cityList":[{"id":"4601","name":"海口市"},{"id":"4602","name":"三亚市"},{"id":"4603","name":"三沙市"},{"id":"469030","szs":"Y","name":"白沙黎族自治县"},{"id":"469035","szs":"Y","name":"保亭黎族苗族自治县"},{"id":"469031","szs":"Y","name":"昌江黎族自治县"},{"id":"469027","szs":"Y","name":"澄迈县"},{"id":"469025","szs":"Y","name":"定安县"},{"id":"469007","szs":"Y","name":"东方市"},{"id":"469003","szs":"Y","name":"儋州市"},{"id":"469033","szs":"Y","name":"乐东黎族自治县"},{"id":"469028","szs":"Y","name":"临高县"},{"id":"469034","szs":"Y","name":"陵水黎族自治县"},{"id":"469002","szs":"Y","name":"琼海市"},{"id":"469036","szs":"Y","name":"琼中黎族苗族自治县"},{"id":"469026","szs":"Y","name":"屯昌县"},{"id":"469005","szs":"Y","name":"文昌市"},{"id":"469006","szs":"Y","name":"万宁市"},{"id":"469001","szs":"Y","name":"五指山市"}],"provinceName":"海南省"},"success":"true"}
