{"data":{"provinceId":"51","countyName":"新津县","townList":[{"id":"11002081","name":"县城"},{"id":"3109167","name":"安西镇"},{"id":"3113389","name":"邓双镇"},{"id":"3110198","name":"方兴镇"},{"id":"2418263","name":"花桥镇"},{"id":"2418277","name":"花源镇"},{"id":"300322674","name":"金花镇"},{"id":"3113509","name":"金华镇"},{"id":"3110294","name":"普兴镇"},{"id":"310187435","name":"太平新镇"},{"id":"3107282","name":"五津镇"},{"id":"300322639","name":"万兴镇"},{"id":"3110091","name":"新平镇"},{"id":"2418421","name":"兴义镇"},{"id":"11133556","name":"羊安镇"},{"id":"3110998","name":"永商镇"},{"id":"300287392","name":"黄渡乡"},{"id":"300287393","name":"龙马乡"},{"id":"300287391","name":"万和乡"},{"id":"11127358","name":"文井乡"},{"id":"330016526","name":"兴乐乡"}],"cityId":"5101","cityName":"成都市","provinceName":"四川省","countyId":"510132"},"success":"true"}
