{"data":{"provinceId":"51","countyName":"大安区","townList":[{"id":"11002088","name":"城区"},{"id":"11407605","name":"艾叶镇"},{"id":"11407610","name":"白庙镇"},{"id":"11407611","name":"成佳镇"},{"id":"2421635","name":"大山铺镇"},{"id":"300522128","name":"富权镇"},{"id":"300473247","name":"富世镇"},{"id":"2421700","name":"回龙镇"},{"id":"300522124","name":"黄市镇"},{"id":"2421663","name":"何市镇"},{"id":"11407604","name":"建设镇"},{"id":"11407621","name":"莲花镇"},{"id":"300522127","name":"联络镇"},{"id":"300522126","name":"龙团镇"},{"id":"11407620","name":"龙潭镇"},{"id":"2421757","name":"庙坝镇"},{"id":"2421778","name":"牛佛镇"},{"id":"11407612","name":"桥头镇"},{"id":"11407613","name":"荣边镇"},{"id":"2421841","name":"三多寨镇"},{"id":"11407616","name":"胜利镇"},{"id":"11407615","name":"舒坪镇"},{"id":"2421868","name":"团结镇"},{"id":"11407614","name":"五宝镇"},{"id":"300522123","name":"瓦市镇"},{"id":"11130344","name":"新店镇"},{"id":"2421897","name":"新民镇"},{"id":"300473246","name":"旭阳镇"},{"id":"300522129","name":"永安镇"},{"id":"11407617","name":"仲权镇"},{"id":"11407601","name":"长土镇"},{"id":"2421650","name":"凤凰乡"},{"id":"11407608","name":"高峰乡"},{"id":"2421683","name":"和平乡"},{"id":"2421692","name":"红旗乡"},{"id":"11407609","name":"农团乡"},{"id":"11407607","name":"牛尾乡"},{"id":"11407606","name":"漆树乡"},{"id":"11407619","name":"塘家坝乡"},{"id":"2421920","name":"永和乡"},{"id":"2421926","name":"永嘉乡"},{"id":"11407618","name":"鸳鸯乡"},{"id":"11407603","name":"章佳乡"}],"cityId":"5103","cityName":"自贡市","provinceName":"四川省","countyId":"510304"},"success":"true"}
