{"data":{"provinceId":"51","countyName":"资中县","townList":[{"id":"11002134","name":"县城"},{"id":"3113801","name":"陈家镇"},{"id":"2446324","name":"发轮镇"},{"id":"2446518","name":"归德镇"},{"id":"2446398","name":"高楼镇"},{"id":"3111933","name":"甘露镇"},{"id":"3107520","name":"公民镇"},{"id":"300522745","name":"金带镇"},{"id":"3113541","name":"金李井镇"},{"id":"3114522","name":"龙结镇"},{"id":"2446671","name":"龙江镇"},{"id":"2446643","name":"骝马镇"},{"id":"2446804","name":"罗泉镇"},{"id":"2446843","name":"马鞍镇"},{"id":"2446871","name":"孟塘镇"},{"id":"3110264","name":"明心寺镇"},{"id":"2446966","name":"配龙镇"},{"id":"3111888","name":"球溪镇"},{"id":"11139739","name":"顺河场镇"},{"id":"3108035","name":"双河镇"},{"id":"3112794","name":"苏家湾镇"},{"id":"3109179","name":"宋家镇"},{"id":"2447134","name":"双龙镇"},{"id":"3110935","name":"水南镇"},{"id":"3111812","name":"狮子镇"},{"id":"3113608","name":"铁佛镇"},{"id":"3108988","name":"太平镇"},{"id":"11128466","name":"文江镇"},{"id":"3107592","name":"兴隆镇"},{"id":"3110120","name":"新桥镇"},{"id":"3113640","name":"银山镇"},{"id":"2447654","name":"渔溪镇"},{"id":"3113492","name":"重龙镇"},{"id":"2447735","name":"走马镇"},{"id":"2446246","name":"豹岭乡"},{"id":"2446235","name":"白庙乡"},{"id":"3103414","name":"板粟桠乡"},{"id":"2446304","name":"翠流乡"},{"id":"2446299","name":"成渝乡"},{"id":"2446318","name":"东合乡"},{"id":"2446511","name":"共荣乡"},{"id":"2446517","name":"广太乡"},{"id":"2446569","name":"国政乡"},{"id":"3104961","name":"红花乡"},{"id":"2446593","name":"黄家乡"},{"id":"2446591","name":"铧头乡"},{"id":"2446597","name":"金带乡"},{"id":"2446627","name":"亢溪乡"},{"id":"2446642","name":"两渡乡"},{"id":"3100988","name":"凉水乡"},{"id":"2446788","name":"龙山乡"},{"id":"2446867","name":"马沿乡"},{"id":"2446964","name":"农家乡"},{"id":"2446998","name":"麒麟乡"},{"id":"2446997","name":"骑龙乡"},{"id":"2447005","name":"清平乡"},{"id":"2447108","name":"双峰乡"},{"id":"330020172","name":"三河乡"},{"id":"2447360","name":"睢家乡"},{"id":"2447050","name":"三块石乡"},{"id":"2447104","name":"石庙乡"},{"id":"2447212","name":"双中乡"},{"id":"2447414","name":"天宝乡"},{"id":"2447465","name":"同川乡"},{"id":"2447415","name":"天池乡"},{"id":"2447416","name":"天恩乡"},{"id":"2447417","name":"天竺乡"},{"id":"3100047","name":"万福乡"},{"id":"2447469","name":"万发乡"},{"id":"2447475","name":"文江乡"},{"id":"2447486","name":"小桥乡"},{"id":"2447556","name":"学田乡"},{"id":"2447686","name":"玉带乡"},{"id":"2447626","name":"拥共乡"},{"id":"2447618","name":"印盒乡"},{"id":"2447558","name":"杨家河乡"},{"id":"2447559","name":"杨泗乡"},{"id":"2447693","name":"张家乡"}],"cityId":"5110","cityName":"内江市","provinceName":"四川省","countyId":"511025"},"success":"true"}
