{"data":{"provinceId":"51","countyName":"名山区","townList":[{"id":"11002185","name":"县城"},{"id":"2480736","name":"百丈镇"},{"id":"2480780","name":"车岭镇"},{"id":"3112492","name":"红星镇"},{"id":"2480835","name":"黑竹镇"},{"id":"2480906","name":"马岭镇"},{"id":"2480932","name":"蒙阳镇"},{"id":"2480997","name":"新店镇"},{"id":"2481035","name":"永兴镇"},{"id":"2480809","name":"城东乡"},{"id":"300300189","name":"红光乡"},{"id":"2480854","name":"红星乡"},{"id":"2480863","name":"红岩乡"},{"id":"2480879","name":"解放乡"},{"id":"2480869","name":"建山乡"},{"id":"2480898","name":"廖场乡"},{"id":"2480888","name":"联江乡"},{"id":"2480918","name":"茅河乡"},{"id":"2480956","name":"前进乡"},{"id":"2480973","name":"双河乡"},{"id":"2480983","name":"万古乡"},{"id":"2481034","name":"永乡"},{"id":"2481059","name":"中峰乡"}],"cityId":"5118","cityName":"雅安市","provinceName":"四川省","countyId":"511821"},"success":"true"}
