{"data":{"provinceId":"51","countyName":"雁江区","townList":[{"id":"11002196","name":"城区"},{"id":"2485768","name":"保和镇"},{"id":"2485747","name":"宝台镇"},{"id":"2485927","name":"东峰镇"},{"id":"2485871","name":"丹山镇"},{"id":"2486048","name":"堪嘉镇"},{"id":"2486071","name":"老君镇"},{"id":"2486151","name":"南津镇"},{"id":"300250974","name":"清泉镇"},{"id":"300250977","name":"松江镇"},{"id":"2486234","name":"石岭镇"},{"id":"2486258","name":"松涛镇"},{"id":"2486313","name":"伍隍镇"},{"id":"2486352","name":"祥符镇"},{"id":"2486386","name":"小院镇"},{"id":"2486480","name":"迎接镇"},{"id":"2486456","name":"雁江镇"},{"id":"2486518","name":"中和镇"},{"id":"2486553","name":"忠义镇"},{"id":"3104757","name":"碑记乡"},{"id":"3100847","name":"八庙乡"},{"id":"3102825","name":"慈祥乡"},{"id":"3100263","name":"东安乡"},{"id":"3101857","name":"大佛乡"},{"id":"3102002","name":"大洪乡"},{"id":"3101955","name":"大明乡"},{"id":"3102030","name":"大腰乡"},{"id":"3101906","name":"大堰乡"},{"id":"3103088","name":"方朝乡"},{"id":"3100415","name":"丰裕乡"},{"id":"3102599","name":"干沟乡"},{"id":"3101399","name":"古井乡"},{"id":"3106331","name":"高龙乡"},{"id":"3103895","name":"河东乡"},{"id":"3100747","name":"侯家坪乡"},{"id":"2486007","name":"回龙乡"},{"id":"3104962","name":"红莲乡"},{"id":"3105754","name":"金带乡"},{"id":"3103114","name":"昆仑乡"},{"id":"3100424","name":"临江乡"},{"id":"3106346","name":"鲁家乡"},{"id":"3101050","name":"刘家乡"},{"id":"11131983","name":"莲台乡"},{"id":"3106595","name":"龙潭乡"},{"id":"3106024","name":"隆相乡"},{"id":"3105062","name":"老鹰乡"},{"id":"3103707","name":"民合乡"},{"id":"3101785","name":"培德乡"},{"id":"3104623","name":"盘石乡"},{"id":"3100024","name":"七里乡"},{"id":"3104113","name":"清泉乡"},{"id":"3104105","name":"清水乡"},{"id":"3104668","name":"石川乡"},{"id":"3101821","name":"塘池乡"},{"id":"3102096","name":"太和乡"},{"id":"3102112","name":"太平乡"},{"id":"3101476","name":"同心乡"},{"id":"3105832","name":"铜钟乡"},{"id":"3100631","name":"五龙乡"},{"id":"2486423","name":"新场乡"},{"id":"3101566","name":"响峒乡"},{"id":"3100446","name":"义和乡"},{"id":"3103357","name":"杨柳乡"},{"id":"3105397","name":"裕通乡"},{"id":"3103758","name":"永太乡"},{"id":"3102891","name":"振书乡"},{"id":"3105891","name":"长生乡"},{"id":"3104922","name":"紫微乡"}],"cityId":"5120","cityName":"资阳市","provinceName":"四川省","countyId":"512002"},"success":"true"}
