{"data":{"provinceId":"51","countyName":"美姑县","townList":[{"id":"11002246","name":"县城"},{"id":"2500931","name":"巴普镇"},{"id":"2500921","name":"巴古乡"},{"id":"2500920","name":"八口乡"},{"id":"2500940","name":"炳途乡"},{"id":"2500946","name":"采红乡"},{"id":"2500954","name":"典补乡"},{"id":"310193567","name":"大桥乡"},{"id":"2500969","name":"尔合乡"},{"id":"2500963","name":"峨曲古乡"},{"id":"2500975","name":"尔其乡"},{"id":"2500997","name":"候播乃拖乡"},{"id":"2500987","name":"合姑洛乡"},{"id":"2501011","name":"候古莫乡"},{"id":"2500981","name":"哈洛乡"},{"id":"310193568","name":"洪溪乡"},{"id":"2501037","name":"九口乡"},{"id":"2501047","name":"觉洛乡"},{"id":"2501025","name":"井叶特西乡"},{"id":"2501112","name":"洛俄依甘乡"},{"id":"2501073","name":"柳洪乡"},{"id":"2501054","name":"拉木阿觉乡"},{"id":"2501084","name":"龙门乡"},{"id":"2501123","name":"洛莫依达乡"},{"id":"2501100","name":"龙窝乡"},{"id":"2501064","name":"乐约乡"},{"id":"310193569","name":"龙竹乡"},{"id":"2501138","name":"尼哈乡"},{"id":"2501143","name":"牛牛坝乡"},{"id":"2501158","name":"农作乡"},{"id":"2501166","name":"洒库乡"},{"id":"2501184","name":"苏洛乡"},{"id":"2501177","name":"树窝乡"},{"id":"2501193","name":"拖木乡"},{"id":"2501199","name":"瓦古乡"},{"id":"2501209","name":"瓦西乡"},{"id":"2501219","name":"依果觉乡"},{"id":"2501232","name":"依洛拉达乡"},{"id":"2501256","name":"佐戈依达乡"},{"id":"2501240","name":"竹库乡"},{"id":"2501247","name":"子威乡"}],"cityId":"5134","cityName":"凉山彝族自治州","provinceName":"四川省","countyId":"513436"},"success":"true"}
