{"data":{"provinceId":"54","countyName":"堆龙德庆县","townList":[{"id":"11002471","name":"县城"},{"id":"2567518","name":"东噶镇"},{"id":"2567511","name":"东嘎镇"},{"id":"2567548","name":"乃琼镇"},{"id":"300291860","name":"比萨乡"},{"id":"11415523","name":"蔡公堂乡"},{"id":"11415524","name":"夺底乡"},{"id":"2567502","name":"德庆乡"},{"id":"2567520","name":"古荣乡"},{"id":"300291861","name":"杰格纳乡"},{"id":"300291862","name":"勒木切乡"},{"id":"2567533","name":"柳梧乡"},{"id":"2567539","name":"马乡"},{"id":"300291858","name":"那嘎乡"},{"id":"11415520","name":"纳金乡"},{"id":"300343872","name":"前进乡"},{"id":"300291859","name":"热鄂乡"},{"id":"300291857","name":"松多俄玛乡"},{"id":"300291863","name":"索隆江果乡"},{"id":"2567565","name":"羊达乡"},{"id":"11415519","name":"藏热乡"}],"cityId":"5401","cityName":"拉萨市","provinceName":"西藏自治区","countyId":"540125"},"success":"true"}
