{"data":{"provinceId":"62","countyName":"天祝藏族自治县","townList":[{"id":"11002670","name":"县城"},{"id":"2628608","name":"安远镇"},{"id":"2628627","name":"打柴沟镇"},{"id":"2628696","name":"哈溪镇"},{"id":"2628711","name":"华藏寺镇"},{"id":"2628773","name":"石门镇"},{"id":"2628760","name":"赛什斯镇"},{"id":"3110534","name":"松山镇"},{"id":"2628801","name":"炭山岭镇"},{"id":"2628666","name":"东大滩乡"},{"id":"2628647","name":"大红沟乡"},{"id":"2628658","name":"旦马乡"},{"id":"3100253","name":"东坪乡"},{"id":"2628679","name":"朵什乡"},{"id":"2628741","name":"毛藏乡"},{"id":"2628747","name":"祁连乡"},{"id":"3105542","name":"赛拉隆乡"},{"id":"2628816","name":"天堂乡"},{"id":"2628835","name":"西大滩乡"},{"id":"2628848","name":"朱岔乡"},{"id":"2628854","name":"抓喜秀龙乡"}],"cityId":"6206","cityName":"武威市","provinceName":"甘肃省","countyId":"620623"},"success":"true"}
