{"data":{"provinceId":"63","countyName":"班玛县","townList":[{"id":"11002757","name":"县城"},{"id":"2649700","name":"赛来塘镇"},{"id":"2649663","name":"班前乡"},{"id":"2649676","name":"多贡麻乡"},{"id":"2649664","name":"达卡乡"},{"id":"2649669","name":"灯塔乡"},{"id":"2649683","name":"吉卡乡"},{"id":"2649687","name":"江日堂乡"},{"id":"2649694","name":"马柯河乡"},{"id":"2649704","name":"下贡麻乡"},{"id":"2649705","name":"亚尔堂乡"},{"id":"2649709","name":"知钦乡"}],"cityId":"6326","cityName":"果洛藏族自治州","provinceName":"青海省","countyId":"632622"},"success":"true"}
