{"data":{"provinceId":"63","countyName":"天峻县","townList":[{"id":"11002771","name":"县城"},{"id":"300324804","name":"江河镇"},{"id":"2650768","name":"新源镇"},{"id":"3102806","name":"快尔玛乡"},{"id":"2650743","name":"龙门乡"},{"id":"3103255","name":"木里乡"},{"id":"3104457","name":"生格乡"},{"id":"300324801","name":"苏里乡"},{"id":"3105928","name":"阳康乡"},{"id":"3104975","name":"织合玛乡"},{"id":"300324803","name":"知合玛乡"},{"id":"2650791","name":"舟群乡"}],"cityId":"6328","cityName":"海西蒙古族藏族自治州","provinceName":"青海省","countyId":"632823"},"success":"true"}
