{"data":{"provinceId":"65","countyName":"巴里坤哈萨克自治县","townList":[{"id":"11002812","name":"县城"},{"id":"2656872","name":"博尔羌吉镇"},{"id":"300325184","name":"巴里坤镇"},{"id":"300325185","name":"大河镇"},{"id":"2656934","name":"奎苏镇"},{"id":"3100839","name":"八墙子乡"},{"id":"2656892","name":"大红柳峡乡"},{"id":"2656924","name":"花园乡"},{"id":"2656907","name":"海子沿乡"},{"id":"2656974","name":"萨尔乔克乡"},{"id":"300325186","name":"石人子乡"},{"id":"3100227","name":"下涝坝乡"},{"id":"2656920","name":"红山农场"},{"id":"12002774","name":"良种场"}],"cityId":"6522","cityName":"哈密地区","provinceName":"新疆维吾尔自治区","countyId":"652222"},"success":"true"}
