{"data":{"provinceId":"65","countyName":"玛纳斯县","townList":[{"id":"11002817","name":"县城"},{"id":"2657600","name":"包家店镇"},{"id":"2657623","name":"北五岔镇"},{"id":"2657739","name":"六户地镇"},{"id":"2657703","name":"乐土驿镇"},{"id":"2657724","name":"凉州户镇"},{"id":"11159060","name":"兰州湾镇"},{"id":"2657757","name":"玛纳斯镇"},{"id":"2657655","name":"广东地乡"},{"id":"11159059","name":"旱卡子滩哈萨克民族乡"},{"id":"11159058","name":"清水河哈萨克族乡"},{"id":"2657791","name":"头工乡"},{"id":"2657783","name":"塔西河哈萨克族民乡"},{"id":"2657735","name":"林场"},{"id":"310083026","name":"玛电工业区"},{"id":"2657867","name":"新湖总场"}],"cityId":"6523","cityName":"昌吉回族自治州","provinceName":"新疆维吾尔自治区","countyId":"652324"},"success":"true"}
