{"data":{"provinceId":"65","countyName":"拜城县","townList":[{"id":"11002839","name":"县城"},{"id":"3109933","name":"拜城镇"},{"id":"2660896","name":"察尔齐镇"},{"id":"310159843","name":"赛里木镇"},{"id":"2661047","name":"铁热克镇"},{"id":"3105949","name":"阿恰塔格乡"},{"id":"3102137","name":"奥特贝希乡"},{"id":"2660886","name":"布隆乡"},{"id":"2660912","name":"大桥乡"},{"id":"2660938","name":"黑英山乡"},{"id":"2660953","name":"黑孜尔乡"},{"id":"2660980","name":"康其乡"},{"id":"310159582","name":"克孜尔乡"},{"id":"2660995","name":"老虎台乡"},{"id":"310159841","name":"米吉克乡"},{"id":"2661051","name":"托克逊乡"},{"id":"2661065","name":"温巴什乡"},{"id":"3100741","name":"依麻木乡"},{"id":"310266341","name":"亚吐尔乡"},{"id":"2660923","name":"大宛其农场"}],"cityId":"6529","cityName":"阿克苏地区","provinceName":"新疆维吾尔自治区","countyId":"652926"},"success":"true"}
